socialchoicekit/__init__.py
socialchoicekit/bistochastic.py
socialchoicekit/data_generation.py
socialchoicekit/deterministic_allocation.py
socialchoicekit/deterministic_matching.py
socialchoicekit/deterministic_multiround.py
socialchoicekit/deterministic_scoring.py
socialchoicekit/deterministic_tournament.py
socialchoicekit/distortion.py
socialchoicekit/elicitation_allocation.py
socialchoicekit/elicitation_matching.py
socialchoicekit/elicitation_utils.py
socialchoicekit/elicitation_voting.py
socialchoicekit/flow.py
socialchoicekit/preflib_utils.py
socialchoicekit/profile_utils.py
socialchoicekit/randomized_allocation.py
socialchoicekit/randomized_scoring.py
socialchoicekit/utils.py
socialchoicekit-1.0.0.dist-info/LICENSE
socialchoicekit-1.0.0.dist-info/METADATA
socialchoicekit-1.0.0.dist-info/WHEEL
socialchoicekit-1.0.0.dist-info/top_level.txt
socialchoicekit-1.0.0.dist-info/RECORD
