Metadata-Version: 2.1
Name: socialchoicekit
Version: 1.0.0
Summary: socialchoicekit aims to be a comprehensive implementation of the most important rules in computational social choice theory.
Home-page: https://github.com/natsuozawa/socialchoicekit
Author: Natsu Ozawa
Author-email: natsuozawa@outlook.com
License: MIT
Keywords: computational social choice,social choice,voting,allocation,matching,algorithmic game theory,game theory
Platform: UNKNOWN
Classifier: Development Status :: 2 - Pre-Alpha
Classifier: Intended Audience :: Developers
Classifier: Intended Audience :: Science/Research
Classifier: License :: OSI Approved :: MIT License
Classifier: Natural Language :: English
Classifier: Programming Language :: Python :: 3
Classifier: Programming Language :: Python :: 3.8
Requires-Dist: numpy
Requires-Dist: scipy
Requires-Dist: preflibtools
